N64RET/__init__.py
N64RET/CTypes/StandardTypesTypedefs.py
N64RET/CTypes/__init__.py
N64RET/Generator/LdScriptImpl.py
N64RET/Generator/N64SplitConfigImpl.py
N64RET/Generator/__init__.py
N64RET/Loader/RomImpl.py
N64RET/Loader/SegmentImpl.py
N64RET/Loader/__init__.py
N64RET/Loader/Abstract/RomInterface.py
N64RET/Loader/Abstract/SegmentInterface.py
N64RET/Loader/Abstract/__init__.py
N64RET/Loader/N64/InternalHeaderStruct.py
N64RET/Loader/N64/N64RomImpl.py
N64RET/Loader/N64/__init__.py
N64RET/Processor/__init__.py
N64RET/Processor/MIPSR/__init__.py
N64RET/Processor/MIPSR/Disassembler/DisasmImpl.py
N64RET/Processor/MIPSR/Disassembler/__init__.py
decomp_framework-0.0.2.dist-info/LICENSE
decomp_framework-0.0.2.dist-info/METADATA
decomp_framework-0.0.2.dist-info/WHEEL
decomp_framework-0.0.2.dist-info/top_level.txt
decomp_framework-0.0.2.dist-info/RECORD
